{"id":608,"type":"simple","author":"Orbit","title":"Бабл + Гам = Orbit","description":"Самый свежий стикерпак, самый свежий поцелуй!","url":"https://vk.com/stickers/orbit","previews":[35,70,140,296,592],"stickers":[{"id":50170,"images":[512]},{"id":50171,"images":[352,512]},{"id":50172,"images":[512]},{"id":50173,"images":[352,512]},{"id":50174,"images":[]},{"id":50175,"images":[512]},{"id":50176,"images":[352,512]},{"id":50177,"images":[352,512]},{"id":50178,"images":[352,512]},{"id":50179,"images":[352,512]},{"id":50180,"images":[352,512]},{"id":50181,"images":[352]},{"id":50182,"images":[352,512]},{"id":50183,"images":[512]},{"id":50184,"images":[512]},{"id":50185,"images":[352,512]}]}