{"id":1181,"type":"simple","author":"Анастасия Кощевец","title":"Носач","description":"На первый взгляд он нелепый примат с длинным носом. Да и на второй тоже. ","url":"https://vk.com/stickers/longnose","previews":[35,70,140,296,592],"stickers":[{"id":57685,"images":[]},{"id":57686,"images":[]},{"id":57687,"images":[]},{"id":57688,"images":[]},{"id":57689,"images":[]},{"id":57690,"images":[]},{"id":57691,"images":[]},{"id":57692,"images":[]},{"id":57693,"images":[]},{"id":57694,"images":[]},{"id":57695,"images":[]},{"id":57696,"images":[]},{"id":57697,"images":[]},{"id":57698,"images":[]},{"id":57699,"images":[]},{"id":57700,"images":[]},{"id":57701,"images":[]},{"id":57702,"images":[]},{"id":57703,"images":[]},{"id":57704,"images":[]},{"id":57705,"images":[]},{"id":57706,"images":[]},{"id":57707,"images":[]},{"id":57708,"images":[]},{"id":57709,"images":[]},{"id":57710,"images":[]},{"id":57711,"images":[]},{"id":57712,"images":[]},{"id":57713,"images":[]},{"id":57714,"images":[]},{"id":57715,"images":[]},{"id":57716,"images":[]},{"id":57717,"images":[]},{"id":57718,"images":[]},{"id":57719,"images":[]},{"id":57720,"images":[]},{"id":57721,"images":[]},{"id":57722,"images":[]},{"id":57723,"images":[]},{"id":57724,"images":[]},{"id":57725,"images":[]},{"id":57726,"images":[]},{"id":57727,"images":[]},{"id":57728,"images":[]},{"id":57729,"images":[]},{"id":57730,"images":[]},{"id":57731,"images":[]},{"id":57732,"images":[]}]}