{"id":36,"type":"simple","author":"Валерий Матюхин","title":"Новогодняя пора","description":"Наконец-то наступила настоящая зима. Соня и Артём вовсю веселятся и готовятся к празднованию Нового года.","url":"https://vk.com/stickers/christmastime","previews":[35,70,140,296,592],"stickers":[{"id":1229,"images":[]},{"id":1230,"images":[]},{"id":1231,"images":[]},{"id":1232,"images":[]},{"id":1233,"images":[]},{"id":1234,"images":[]},{"id":1235,"images":[]},{"id":1236,"images":[]},{"id":1237,"images":[]},{"id":1238,"images":[]},{"id":1239,"images":[]},{"id":1240,"images":[]},{"id":1241,"images":[]},{"id":1242,"images":[]},{"id":1243,"images":[]},{"id":1244,"images":[]},{"id":1245,"images":[]},{"id":1246,"images":[]},{"id":1247,"images":[]},{"id":1248,"images":[]},{"id":1249,"images":[]},{"id":1250,"images":[]},{"id":1251,"images":[]},{"id":2486,"images":[]}]}