{"id":6,"type":"simple","author":"Валерия Фортуна","title":"Футбол 2014","description":"Яркие эмоции, накал страстей и заряд позитива — поделись атрибутами настоящего футбольного фаната со своими друзьями!","url":"https://vk.com/stickers/football2014","previews":[35,70,140,296,592],"stickers":[{"id":209,"images":[]},{"id":210,"images":[]},{"id":211,"images":[]},{"id":212,"images":[]},{"id":213,"images":[256,512]},{"id":214,"images":[]},{"id":215,"images":[512]},{"id":216,"images":[]},{"id":217,"images":[]},{"id":218,"images":[]},{"id":219,"images":[]},{"id":220,"images":[256,352,512]},{"id":222,"images":[]},{"id":223,"images":[]},{"id":224,"images":[]},{"id":225,"images":[512]},{"id":226,"images":[512]},{"id":227,"images":[]},{"id":228,"images":[]},{"id":229,"images":[]},{"id":231,"images":[]},{"id":232,"images":[]},{"id":337,"images":[]},{"id":338,"images":[]}]}