{"id":378,"type":"simple","author":"Юлия Каменская","title":"Уфо","description":"Инопланетный желток? Космокозявка? Называйте как хотите, но этот неопознанный объект намерен посетить ваши диалоги!","url":"https://vk.com/stickers/ufo","previews":[35,70,140,296,592],"stickers":[{"id":12918,"images":[]},{"id":12919,"images":[]},{"id":12920,"images":[512]},{"id":12921,"images":[]},{"id":12922,"images":[]},{"id":12923,"images":[]},{"id":12924,"images":[]},{"id":12925,"images":[]},{"id":12926,"images":[]},{"id":12927,"images":[]},{"id":12928,"images":[]},{"id":12929,"images":[]},{"id":12930,"images":[]},{"id":12931,"images":[512]},{"id":12932,"images":[512]},{"id":12933,"images":[]},{"id":12934,"images":[]},{"id":12935,"images":[]},{"id":12936,"images":[]},{"id":12937,"images":[]},{"id":12938,"images":[]},{"id":12939,"images":[]},{"id":12940,"images":[512]},{"id":12941,"images":[]},{"id":12942,"images":[]},{"id":12943,"images":[]},{"id":12944,"images":[]},{"id":12945,"images":[]},{"id":12946,"images":[]},{"id":12947,"images":[]},{"id":12948,"images":[]},{"id":12949,"images":[]},{"id":12950,"images":[]},{"id":12951,"images":[512]},{"id":12952,"images":[512]},{"id":12953,"images":[]},{"id":12954,"images":[]},{"id":12955,"images":[]},{"id":12956,"images":[]},{"id":12957,"images":[]},{"id":12958,"images":[]},{"id":12959,"images":[]},{"id":12960,"images":[]},{"id":12961,"images":[]},{"id":12962,"images":[]},{"id":12963,"images":[]},{"id":12964,"images":[]},{"id":12965,"images":[]},{"id":19685,"images":[]}]}