{"id":1216,"type":"simple","author":"Валерий Матюхин","title":"Попка","description":"Попугай влетел в форточку как ураган, перебил посуду, спрятался на шкафу и орёт... до сих пор. Похоже, теперь он живёт с нами. ","url":"https://vk.com/stickers/polly","previews":[35,70,140,296,592],"stickers":[{"id":59072,"images":[64]},{"id":59073,"images":[64]},{"id":59074,"images":[64]},{"id":59075,"images":[64]},{"id":59076,"images":[64]},{"id":59077,"images":[64]},{"id":59078,"images":[64]},{"id":59079,"images":[64]},{"id":59080,"images":[64]},{"id":59081,"images":[64]},{"id":59082,"images":[64]},{"id":59083,"images":[64]},{"id":59084,"images":[64]},{"id":59085,"images":[512]},{"id":59086,"images":[64]},{"id":59087,"images":[64]},{"id":59088,"images":[64]},{"id":59089,"images":[64]},{"id":59090,"images":[64]},{"id":59091,"images":[352]},{"id":59092,"images":[64]},{"id":59093,"images":[64]},{"id":59094,"images":[]},{"id":59095,"images":[512]},{"id":59096,"images":[512]},{"id":59097,"images":[64]},{"id":59098,"images":[64]},{"id":59099,"images":[64]},{"id":59100,"images":[64]},{"id":59101,"images":[64]},{"id":59102,"images":[64]},{"id":59103,"images":[64]},{"id":59104,"images":[64]},{"id":59105,"images":[]},{"id":59106,"images":[512]},{"id":59107,"images":[64]},{"id":59108,"images":[64]},{"id":59109,"images":[64]},{"id":59110,"images":[]},{"id":59111,"images":[64]},{"id":59112,"images":[64]},{"id":59113,"images":[64]},{"id":59114,"images":[64]},{"id":59115,"images":[]},{"id":59116,"images":[64]},{"id":59117,"images":[64]},{"id":59118,"images":[64]},{"id":59119,"images":[512]}]}