{"id":238,"type":"simple","author":"Delivery Club","title":"Страус Дели","description":"Стикеры, которые доставляют.","url":"https://vk.com/stickers/dc","previews":[35,70,140,296],"stickers":[{"id":7798,"images":[128]},{"id":7799,"images":[128]},{"id":7800,"images":[128]},{"id":7801,"images":[]},{"id":7802,"images":[128,256]},{"id":7803,"images":[]},{"id":7804,"images":[]},{"id":7805,"images":[]},{"id":7806,"images":[512]},{"id":7807,"images":[]},{"id":7808,"images":[]},{"id":7809,"images":[]},{"id":7810,"images":[]},{"id":7811,"images":[]},{"id":7812,"images":[]},{"id":7813,"images":[]}]}