{"id":336,"type":"simple","author":"Антон Андреев","title":"Зимние друзья","description":"Неважно, при какой температуре проводишь время, важно в какой компании!","url":"https://vk.com/stickers/winterfriends","previews":[35,70,140],"stickers":[{"id":11142,"images":[]},{"id":11143,"images":[]},{"id":11144,"images":[]},{"id":11145,"images":[]},{"id":11146,"images":[]},{"id":11147,"images":[]},{"id":11148,"images":[]},{"id":11149,"images":[]},{"id":11150,"images":[]},{"id":11151,"images":[]},{"id":11152,"images":[512]},{"id":11153,"images":[]},{"id":11154,"images":[]},{"id":11155,"images":[512]},{"id":11156,"images":[]},{"id":11157,"images":[]},{"id":11158,"images":[]},{"id":11159,"images":[]},{"id":11160,"images":[]},{"id":11161,"images":[]},{"id":11162,"images":[]},{"id":11163,"images":[]},{"id":11164,"images":[]},{"id":11165,"images":[]},{"id":11166,"images":[]},{"id":11167,"images":[]},{"id":11168,"images":[]},{"id":11169,"images":[]},{"id":11170,"images":[]},{"id":11171,"images":[]},{"id":11172,"images":[]},{"id":11173,"images":[]},{"id":11174,"images":[]},{"id":11175,"images":[512]},{"id":11176,"images":[]},{"id":11177,"images":[]},{"id":11178,"images":[]},{"id":11179,"images":[]},{"id":11180,"images":[]},{"id":11181,"images":[]},{"id":11182,"images":[]},{"id":11183,"images":[512]},{"id":11184,"images":[512]},{"id":11185,"images":[]},{"id":11186,"images":[]},{"id":11187,"images":[]},{"id":11188,"images":[]},{"id":11189,"images":[]}]}