{"id":1017,"type":"simple","author":"Антон Андреев","title":"Айко-тян","description":"К нам прибыла ученица по обмену — прямиком из Японии! Айко-тян сложно быть новенькой: кругом незнакомые люди, непонятный язык. Но можно общаться стикерами!","url":"https://vk.com/stickers/aiko","previews":[35,70,140,296,592],"stickers":[{"id":50596,"images":[]},{"id":50597,"images":[]},{"id":50598,"images":[]},{"id":50599,"images":[]},{"id":50600,"images":[]},{"id":50601,"images":[]},{"id":50602,"images":[]},{"id":50603,"images":[]},{"id":50604,"images":[]},{"id":50605,"images":[]},{"id":50606,"images":[]},{"id":50607,"images":[]},{"id":50608,"images":[]},{"id":50609,"images":[]},{"id":50610,"images":[]},{"id":50611,"images":[]},{"id":50612,"images":[]},{"id":50613,"images":[]},{"id":50614,"images":[]},{"id":50615,"images":[]},{"id":50616,"images":[]},{"id":50617,"images":[]},{"id":50618,"images":[]},{"id":50619,"images":[]},{"id":50620,"images":[]},{"id":50621,"images":[]},{"id":50622,"images":[]},{"id":50623,"images":[]},{"id":50624,"images":[]},{"id":50625,"images":[]},{"id":50626,"images":[]},{"id":50627,"images":[]},{"id":50628,"images":[]},{"id":50629,"images":[]},{"id":50630,"images":[]},{"id":50631,"images":[]},{"id":50632,"images":[]},{"id":50633,"images":[]},{"id":50634,"images":[]},{"id":50635,"images":[]},{"id":50636,"images":[]},{"id":50637,"images":[]},{"id":50638,"images":[]},{"id":50639,"images":[]},{"id":50640,"images":[]},{"id":50641,"images":[]},{"id":50642,"images":[]},{"id":50643,"images":[]}]}