{"id":1014,"type":"simple","author":"Ирина Брэдкэт","title":"Мох","description":"Слишком опасно идти в одиночку! Возьмите с собой пушистого компаньона. Малыш Мох носит в щёчках запасы на все случаи жизни — и поделится с вами, если станете ему другом.","url":"https://vk.com/stickers/hammy","previews":[35,70,140,296,592],"stickers":[{"id":50451,"images":[]},{"id":50452,"images":[64,512]},{"id":50453,"images":[64,512]},{"id":50454,"images":[64,512]},{"id":50455,"images":[]},{"id":50456,"images":[64,512]},{"id":50457,"images":[64,512]},{"id":50458,"images":[]},{"id":50459,"images":[]},{"id":50460,"images":[512]},{"id":50461,"images":[]},{"id":50462,"images":[]},{"id":50463,"images":[]},{"id":50464,"images":[]},{"id":50465,"images":[]},{"id":50466,"images":[]},{"id":50467,"images":[]},{"id":50468,"images":[]},{"id":50469,"images":[]},{"id":50470,"images":[]},{"id":50471,"images":[]},{"id":50472,"images":[]},{"id":50473,"images":[]},{"id":50474,"images":[]},{"id":50475,"images":[]},{"id":50476,"images":[]},{"id":50477,"images":[]},{"id":50478,"images":[]},{"id":50479,"images":[]},{"id":50480,"images":[]},{"id":50481,"images":[]},{"id":50482,"images":[]},{"id":50483,"images":[]},{"id":50484,"images":[]},{"id":50485,"images":[]},{"id":50486,"images":[]},{"id":50487,"images":[]},{"id":50488,"images":[]},{"id":50489,"images":[]},{"id":50490,"images":[]},{"id":50491,"images":[]},{"id":50492,"images":[]},{"id":50493,"images":[]},{"id":50494,"images":[]},{"id":50495,"images":[]},{"id":50496,"images":[]},{"id":50497,"images":[]},{"id":50498,"images":[]}]}